{
    "$schema": "https://schema.management.azure.com/schemas/2015-01-01/deploymentParameters.json#",
    "contentVersion": "1.0.0.0",
    "parameters": {
        "apimName": {
            "value": "api-z-cplusgw-p-001"
        },
        "skuName": {
            "value": "Premium"
        },
        "publisherEmail": {
            "value": "dagarwal@emerson.com"
        },
        "virtualNetworkName": {
            "value": "vnet-z-cplusgw-p-001"
        },
        "subnetName": {
            "value": "sn-z-cplus-infragw"
        },
        "publicIPAddressesName": {
            "value": "pip-z-cplus-api-p-001"
        },
        "capacity": {
            "value": "1"
        },
        "identity": {
            "value": {
                "type": "None"
            }
        }
    }
}
